monk_de.py
monk_de-0.3.1.dist-info/METADATA
monk_de-0.3.1.dist-info/DESCRIPTION.rst
monk_de-0.3.1.dist-info/WHEEL
monk_de-0.3.1.dist-info/entry_points.txt
monk_de-0.3.1.dist-info/metadata.json
monk_de-0.3.1.dist-info/top_level.txt
monk_de-0.3.1.dist-info/RECORD
