Metadata-Version: 2.0
Name: monk-de
Version: 0.3.1
Summary: Tmuxinator like tooling in python
Home-page: https://github.com/DFE/monk_de
Author: DResearch Fahrzeugelektronik GmbH
Author-email: project-monk@dresearch-fe.de
License: UNKNOWN
Platform: UNKNOWN
Provides: monk_de (0.3.1)
